{
    "Seb": 2976305,
    "Dan": 1700879,
    "SUPER PAPPY": 2051573,
    "SombreRow": 1974559,
    "Antman": 2064865,
    "Dave the mason": 746971,
    "alex": 2761078,
    "NikE_PhiL": 646910,
    "Luc¥ f€r": 1819825,
    "superrsebasss": 1302977,
    "Dan ⚜": 1321753,
    "3JOH22A": 1301511,
    "••chr!s••": 2218128,
    "Cowboy": 1162620,
    "cacoulie": 383041,
    "bandit2207": 254281,
    "destructor": 355597,
    "DUST2JERK": 2234505,
    "Momess": 594625,
    "Bigben031340": 4600,
    "Sly": 1905646,
    "Constellation": 1347974,
    "sir warriors": 1527972,
    "math": 1066490,
    "CatchMeIfYouCan": 336341,
    "steevepremier": 218050,
    "Fleck": 1227588,
    "Shxprz": 189533,
    "Dave The Great": 1682795,
    "Dragonne": 20450,
    "quiny": 1045734,
    "KiL0": 826565,
    "rochy": 963670,
    "Le_Québecois": 271376,
    "⚡️oli26⚡️": 202708,
    "rocket": 144864,
    "Coco": 27220,
    "⚜️Chef Menta⚜️": 100,
    "Loup Solitaire": 227552,
    "Vozcom": 358682,
    "gallagher": 126868,
    "Aria": 160863,
    "kass": 694919,
    "MasterProulx": 686405,
    "The Grizz": 303734,
    "Calipso": 1288283,
    "Jacky": 473839,
    "⭐️DeadShot⭐️": 92485,
    "Volcanojet3": 220903,
    "Cheevo": 1090411,
    "Sir.Anas": 100,
    "Lecoune": 416106,
    "Ticoune76": 950492,
    "Glorryk2.0": 292986,
    "Glorryk 1": 305531,
    "Justin07": 935748,
    "SimTheGrinch": 1317705,
    "Shrek": 1822236,
    "Kenzy": 780580,
    "hulk": 1697913,
    "vincent": 528599,
    "DamselM": 1320567,
    "Andynator": 492730,
    "Rastafa": 925113,
    "Whi$$": 627450,
    "jag": 245812,
    "cochongamer2000": 713706,
    "MOÉ L'King": 355691,
    "juju": 675361,
    "joey": 450750,
    "mothertanker": 187900,
    "tikevrocket": 810020,
    "Cpt.Taloche": 64186
}